LICENSE
MANIFEST.in
README.md
setup.py
django_lint2.egg-info/PKG-INFO
django_lint2.egg-info/SOURCES.txt
django_lint2.egg-info/dependency_links.txt
django_lint2.egg-info/top_level.txt
lint2/__init__.py
lint2/checks.py